README.md
setup.cfg
setup.py
router_status/__init__.py
router_status/__main__.py
router_status.egg-info/PKG-INFO
router_status.egg-info/SOURCES.txt
router_status.egg-info/dependency_links.txt
router_status.egg-info/top_level.txt
router_status/models/__init__.py
router_status/models/bt_smart_hub_2.py
router_status/models/common.py
router_status/models/errors.py